LICENSE
MANIFEST.in
README.md
README.rst
setup.cfg
setup.py
cronquot/__init__.py
cronquot/cronquot.py
cronquot.egg-info/PKG-INFO
cronquot.egg-info/SOURCES.txt
cronquot.egg-info/dependency_links.txt
cronquot.egg-info/entry_points.txt
cronquot.egg-info/requires.txt
cronquot.egg-info/top_level.txt
test/test_cronquot.py