Metadata-Version: 1.1
Name: cronquot
Version: 0.1.0
Summary: Cron scheduler.
Home-page: https://github.com/pyohei/cronquot
Author: Shohei Mukai
Author-email: mukaishohei76@gmail.com
License: MIT
Keywords: cron crontab schedule
Platform: UNKNOWN
Classifier: Programming Language :: Python
Classifier: Programming Language :: Python :: 2.7
Classifier: License :: OSI Approved :: MIT License
Classifier: Topic :: Software Development :: Libraries :: Python Modules
